nme/__init__.py
nme-0.1.8.dist-info/LICENSE
nme-0.1.8.dist-info/METADATA
nme-0.1.8.dist-info/WHEEL
nme-0.1.8.dist-info/top_level.txt
nme-0.1.8.dist-info/RECORD
